lilygo_tdeck.py
circuitpython_lilygo_t_deck-0.1.1.dist-info/LICENSE
circuitpython_lilygo_t_deck-0.1.1.dist-info/METADATA
circuitpython_lilygo_t_deck-0.1.1.dist-info/WHEEL
circuitpython_lilygo_t_deck-0.1.1.dist-info/top_level.txt
circuitpython_lilygo_t_deck-0.1.1.dist-info/RECORD
