Metadata-Version: 2.1
Name: circuitpython-lilygo-t-deck
Version: 0.1.1
Summary: CircuitPython drivers for the LILYGO T-Deck peripherals.
Author-email: Robert Grizzell <robert@grizzell.me>
License: MIT
Project-URL: Homepage, https://github.com/rgrizzell/CircuitPython_LILYGO_T-Deck
Keywords: adafruit,blinka,circuitpython,micropython,lilygo-tdeck,lilygo,t-deck
Classifier: Intended Audience :: Developers
Classifier: Topic :: Software Development :: Libraries
Classifier: Topic :: Software Development :: Embedded Systems
Classifier: Topic :: System :: Hardware
Classifier: License :: OSI Approved :: MIT License
Classifier: Programming Language :: Python :: 3
License-File: LICENSE
Requires-Dist: Adafruit-Blinka
Provides-Extra: optional
